dotcausal/__init__.py
dotcausal/cli.py
dotcausal/core.py
dotcausal/inference.py
dotcausal/io.py
dotcausal/langchain.py
dotcausal-0.3.1.dist-info/METADATA
dotcausal-0.3.1.dist-info/WHEEL
dotcausal-0.3.1.dist-info/entry_points.txt
dotcausal-0.3.1.dist-info/licenses/LICENSE
dotcausal-0.3.1.dist-info/RECORD
