Metadata-Version: 2.4
Name: dotcausal
Version: 0.3.1
Summary: Binary Knowledge Graph Format with Embedded Inference for AI Applications
Project-URL: Homepage, https://dotcausal.com
Project-URL: Documentation, https://dotcausal.com/docs
Project-URL: Repository, https://github.com/dotcausal/dotcausal
Project-URL: Changelog, https://github.com/dotcausal/dotcausal/blob/main/CHANGELOG.md
Author-email: David Tom Foss <david@foss.com.de>
License: MIT
License-File: LICENSE
Keywords: ai,binary-format,causal-inference,knowledge-graph,llm,rag,triplets,zero-hallucination
Classifier: Development Status :: 4 - Beta
Classifier: Intended Audience :: Developers
Classifier: Intended Audience :: Science/Research
Classifier: License :: OSI Approved :: MIT License
Classifier: Operating System :: OS Independent
Classifier: Programming Language :: Python :: 3
Classifier: Programming Language :: Python :: 3.9
Classifier: Programming Language :: Python :: 3.10
Classifier: Programming Language :: Python :: 3.11
Classifier: Programming Language :: Python :: 3.12
Classifier: Topic :: Database
Classifier: Topic :: File Formats
Classifier: Topic :: Scientific/Engineering :: Artificial Intelligence
Requires-Python: >=3.9
Requires-Dist: click>=8.0.0
Requires-Dist: msgpack>=1.0.0
Requires-Dist: xxhash>=3.0.0
Provides-Extra: all
Requires-Dist: langchain-core>=0.2.0; extra == 'all'
Provides-Extra: dev
Requires-Dist: black>=23.0.0; extra == 'dev'
Requires-Dist: pytest-cov>=4.0.0; extra == 'dev'
Requires-Dist: pytest>=7.0.0; extra == 'dev'
Requires-Dist: ruff>=0.1.0; extra == 'dev'
Provides-Extra: langchain
Requires-Dist: langchain-core>=0.2.0; extra == 'langchain'
